erosmb/Machine.py
erosmb/SMBScanner.py
erosmb/__init__.py
EroSmb-0.1.5.dist-info/LICENSE
EroSmb-0.1.5.dist-info/METADATA
EroSmb-0.1.5.dist-info/WHEEL
EroSmb-0.1.5.dist-info/entry_points.txt
EroSmb-0.1.5.dist-info/top_level.txt
EroSmb-0.1.5.dist-info/RECORD
