Metadata-Version: 2.1
Name: EroSmb
Version: 0.1.5
Summary: EroSmb is a fast smb network scanner
License: MIT
Keywords: smb,scanner,security,enumeration,infosec,pentest
License-File: LICENSE
Requires-Dist: impacket
Requires-Dist: colorama
